sophone/__init__.py
sophone/cli.py
sophone/core.py
sophone-0.1.0.dist-info/METADATA
sophone-0.1.0.dist-info/WHEEL
sophone-0.1.0.dist-info/entry_points.txt
sophone-0.1.0.dist-info/top_level.txt
sophone-0.1.0.dist-info/RECORD
