Metadata-Version: 2.4
Name: sophone
Version: 0.1.0
Summary: Validate & format Somali phone numbers (+252) with provider detection
Author-email: Omar Tood <omartood@example.com>
License-Expression: MIT
Keywords: Somalia,Somali,phone,validation,E164,telecom,+252
Requires-Python: >=3.8
